setup.py
flask_easy_login/__init__.py
flask_easy_login.egg-info/PKG-INFO
flask_easy_login.egg-info/SOURCES.txt
flask_easy_login.egg-info/dependency_links.txt
flask_easy_login.egg-info/requires.txt
flask_easy_login.egg-info/top_level.txt