Metadata-Version: 1.0
Name: flask-easy-login
Version: 0.0.3
Summary: flask_login
Home-page: UNKNOWN
Author: UNKNOWN
Author-email: UNKNOWN
License: UNKNOWN
Platform: UNKNOWN
